cprov/__init__.py
cprov/_version.py
cprov/cli.py
cprov/common.py
cprov/utils.py
cprov/commands/__init__.py
cprov/commands/do.py
cprov/commands/status.py
cprov-0.0.5.dist-info/METADATA
cprov-0.0.5.dist-info/WHEEL
cprov-0.0.5.dist-info/entry_points.txt
cprov-0.0.5.dist-info/top_level.txt
cprov-0.0.5.dist-info/RECORD
